voicetranslator/LICENSE.txt
voicetranslator/__init__.py
voicetranslator/_voicetranslator.py
voicetranslator/libgcc_s_seh-1.dll
voicetranslator/libstdc++-6.dll
voicetranslator/libwinpthread-1.dll
voicetranslator/voicetranslator.exe
voicetranslator-1.3.0.dist-info/LICENSE
voicetranslator-1.3.0.dist-info/METADATA
voicetranslator-1.3.0.dist-info/WHEEL
voicetranslator-1.3.0.dist-info/top_level.txt
voicetranslator-1.3.0.dist-info/RECORD
